ivlog_cli/__init__.py
ivlog_cli/arg_praser.py
ivlog_cli/list_tb.py
ivlog_cli/new_ivlog_project.py
ivlog_cli/run_iverilog.py
ivlog_cli/tb_manager.py
ivlog_cli-0.1.2.dist-info/entry_points.txt
ivlog_cli-0.1.2.dist-info/METADATA
ivlog_cli-0.1.2.dist-info/WHEEL
ivlog_cli-0.1.2.dist-info/RECORD
