Metadata-Version: 2.1
Name: ivlog-cli
Version: 0.1.2
Summary: iverilog tools
License: MIT
Author: zhao-leo
Author-email: zhao@zhaocloud.work
Requires-Python: >=3.12,<4.0
Classifier: License :: OSI Approved :: MIT License
Classifier: Programming Language :: Python :: 3
Classifier: Programming Language :: Python :: 3.12
Requires-Dist: toml (>=0.10.2,<0.11.0)
